gdrive_suite/__init__.py
gdrive_suite/gdrive_exceptions.py
gdrive_suite/context/__init__.py
gdrive_suite/context/models.py
gdrive_suite/drive/__init__.py
gdrive_suite/drive/gdrive_client.py
gdrive_suite/drive/gdrive_client_config.py
gdrive_suite-0.2.0.dist-info/licenses/LICENSE
gdrive_suite-0.2.0.dist-info/METADATA
gdrive_suite-0.2.0.dist-info/WHEEL
gdrive_suite-0.2.0.dist-info/top_level.txt
gdrive_suite-0.2.0.dist-info/RECORD
