Metadata-Version: 2.4
Name: gdrive-suite
Version: 0.2.0
Summary: A Python library for interacting with Google Drive and Google Sheets.
Author-email: TheLionCoder <eorlando.reyesruiz@gmail.com>
License: MIT License
Project-URL: Homepage, https://github.com/TheLionCoder/gdrive-suite
Project-URL: Bug Tracker, https://github.com/TheLionCoder/gdrive-suite/issues
Classifier: Programming Language :: Python :: 3
Classifier: Programming Language :: Python :: 3.11
Classifier: Programming Language :: Python :: 3.12
Classifier: Programming Language :: Python :: 3.13
Classifier: License :: OSI Approved :: MIT License
Classifier: Operating System :: OS Independent
Classifier: Intended Audience :: Developers
Classifier: Topic :: Software Development :: Libraries :: Python Modules
Classifier: Topic :: Internet
Requires-Python: >=3.11
License-File: LICENSE
Requires-Dist: google-api-python-client>=2.162.0
Requires-Dist: google-auth-oauthlib>=1.2.1
Requires-Dist: loguru>=0.7.3
Provides-Extra: dev
Requires-Dist: types-pyyaml>=6.0.12.20250516; extra == "dev"
Requires-Dist: google-api-python-client-stubs; extra == "dev"
Requires-Dist: google-auth-stubs; extra == "dev"
Requires-Dist: build; extra == "dev"
Requires-Dist: twine; extra == "dev"
Requires-Dist: mkdocs>=1.6.1; extra == "dev"
Requires-Dist: mkdocs-material>=9.6.18; extra == "dev"
Requires-Dist: mkdocstrings-python>=1.18.2; extra == "dev"
Requires-Dist: pyright>=1.1.405; extra == "dev"
Dynamic: license-file
